dnacentersdk/__init__.py
dnacentersdk/_metadata.py
dnacentersdk/api/__init__.py
dnacentersdk/api/authentication.py
dnacentersdk/api/custom_caller.py
dnacentersdk/api/v2_3_5_3/__init__.py
dnacentersdk/api/v2_3_5_3/application_policy.py
dnacentersdk/api/v2_3_5_3/applications.py
dnacentersdk/api/v2_3_5_3/authentication_management.py
dnacentersdk/api/v2_3_5_3/cisco_dna_center_system.py
dnacentersdk/api/v2_3_5_3/clients.py
dnacentersdk/api/v2_3_5_3/command_runner.py
dnacentersdk/api/v2_3_5_3/compliance.py
dnacentersdk/api/v2_3_5_3/configuration_archive.py
dnacentersdk/api/v2_3_5_3/configuration_templates.py
dnacentersdk/api/v2_3_5_3/device_onboarding_pnp.py
dnacentersdk/api/v2_3_5_3/device_replacement.py
dnacentersdk/api/v2_3_5_3/devices.py
dnacentersdk/api/v2_3_5_3/discovery.py
dnacentersdk/api/v2_3_5_3/eox.py
dnacentersdk/api/v2_3_5_3/event_management.py
dnacentersdk/api/v2_3_5_3/fabric_wireless.py
dnacentersdk/api/v2_3_5_3/file.py
dnacentersdk/api/v2_3_5_3/health_and_performance.py
dnacentersdk/api/v2_3_5_3/issues.py
dnacentersdk/api/v2_3_5_3/itsm.py
dnacentersdk/api/v2_3_5_3/itsm_integration.py
dnacentersdk/api/v2_3_5_3/lan_automation.py
dnacentersdk/api/v2_3_5_3/licenses.py
dnacentersdk/api/v2_3_5_3/network_settings.py
dnacentersdk/api/v2_3_5_3/path_trace.py
dnacentersdk/api/v2_3_5_3/platform.py
dnacentersdk/api/v2_3_5_3/reports.py
dnacentersdk/api/v2_3_5_3/sda.py
dnacentersdk/api/v2_3_5_3/security_advisories.py
dnacentersdk/api/v2_3_5_3/sensors.py
dnacentersdk/api/v2_3_5_3/site_design.py
dnacentersdk/api/v2_3_5_3/sites.py
dnacentersdk/api/v2_3_5_3/software_image_management_swim.py
dnacentersdk/api/v2_3_5_3/system_settings.py
dnacentersdk/api/v2_3_5_3/tag.py
dnacentersdk/api/v2_3_5_3/task.py
dnacentersdk/api/v2_3_5_3/topology.py
dnacentersdk/api/v2_3_5_3/user_and_roles.py
dnacentersdk/api/v2_3_5_3/users.py
dnacentersdk/api/v2_3_5_3/wireless.py
dnacentersdk/api/v2_3_7_6/__init__.py
dnacentersdk/api/v2_3_7_6/ai_endpoint_analytics.py
dnacentersdk-2.9.1.dist-info/LICENSE
dnacentersdk-2.9.1.dist-info/METADATA
dnacentersdk-2.9.1.dist-info/WHEEL
dnacentersdk-2.9.1.dist-info/RECORD
