Metadata-Version: 2.1
Name: dnacentersdk
Version: 2.9.1
Summary: Cisco DNA Center Platform SDK
Home-page: https://dnacentersdk.readthedocs.io/en/latest/
License: MIT
Keywords: Cisco,DNA Center,SDK
Author: Jose Bogarin Solano
Author-email: jbogarin@altus.cr
Requires-Python: >=3.8,<4.0
Classifier: License :: OSI Approved :: MIT License
Classifier: Programming Language :: Python :: 3
Classifier: Programming Language :: Python :: 3.8
Classifier: Programming Language :: Python :: 3.9
Classifier: Programming Language :: Python :: 3.10
Classifier: Programming Language :: Python :: 3.11
Classifier: Programming Language :: Python :: 3.12
Requires-Dist: fastjsonschema (>=2.16.2,<3.0.0)
Requires-Dist: requests (>=2.32.0,<3.0.0)
Requires-Dist: requests-toolbelt (>=1.0.0,<2.0.0)
Project-URL: Repository, https://github.com/cisco-en-programmability/dnacentersdk
